odoo/addons/connector_pms/README.rst
odoo/addons/connector_pms/__init__.py
odoo/addons/connector_pms/__manifest__.py
odoo/addons/connector_pms/components/__init__.py
odoo/addons/connector_pms/components/adapter.py
odoo/addons/connector_pms/components/binder.py
odoo/addons/connector_pms/components/core.py
odoo/addons/connector_pms/components/deleter.py
odoo/addons/connector_pms/components/exporter.py
odoo/addons/connector_pms/components/importer.py
odoo/addons/connector_pms/components/mapper_export.py
odoo/addons/connector_pms/components/mapper_import.py
odoo/addons/connector_pms/components_custom/__init__.py
odoo/addons/connector_pms/components_custom/binder.py
odoo/addons/connector_pms/components_custom/exporter.py
odoo/addons/connector_pms/components_custom/importer.py
odoo/addons/connector_pms/components_custom/mapper.py
odoo/addons/connector_pms/data/queue_data.xml
odoo/addons/connector_pms/models/__init__.py
odoo/addons/connector_pms/models/pms_reservation.py
odoo/addons/connector_pms/models/queue_job.py
odoo/addons/connector_pms/models/common/__init__.py
odoo/addons/connector_pms/models/common/backend.py
odoo/addons/connector_pms/models/common/backend_log.py
odoo/addons/connector_pms/models/common/backend_method.py
odoo/addons/connector_pms/models/common/backend_type.py
odoo/addons/connector_pms/models/common/binding.py
odoo/addons/connector_pms/readme/CONTRIBUTORS.rst
odoo/addons/connector_pms/readme/DESCRIPTION.rst
odoo/addons/connector_pms/readme/USAGE.rst
odoo/addons/connector_pms/security/ir.model.access.csv
odoo/addons/connector_pms/static/description/icon.png
odoo/addons/connector_pms/static/description/index.html
odoo/addons/connector_pms/views/channel_backend_log_views.xml
odoo/addons/connector_pms/views/channel_backend_method_views.xml
odoo/addons/connector_pms/views/channel_backend_type_views.xml
odoo/addons/connector_pms/views/channel_backend_views.xml
odoo/addons/connector_pms/views/channel_menus.xml
odoo14_addon_connector_pms-14.0.1.0.1.dev44.dist-info/METADATA
odoo14_addon_connector_pms-14.0.1.0.1.dev44.dist-info/WHEEL
odoo14_addon_connector_pms-14.0.1.0.1.dev44.dist-info/top_level.txt
odoo14_addon_connector_pms-14.0.1.0.1.dev44.dist-info/RECORD
